[
    {
        "key": "db0",
        "value": [
            {
                "key": "Users0",
                "value": [
                    {
                        "key": 0,
                        "value": {
                            "token": "OBWpLJ21",
                            "createdAt": "+057060-11-25T00:09:19.000Z",
                            "username": "HlUnmhdNWJK3JugB",
                            "password": "iBWX0sVDhtSnsvkGf5LXayHcHN68dr77NqPT7xdjbtncyMBkLLJsMWazKOHFPY4k",
                            "email": "nVl9rIxOGykL0deB@cVSZ.VM",
                            "country": "HlUnmhdNWJK3JugB"
                        }
                    }
                ]
            }
        ]
    }
]